p_system_simulate/PSystem.py
p_system_simulate/__init__.py
p_system_simulate/membrane.py
p_system_simulate-0.0.4.dist-info/METADATA
p_system_simulate-0.0.4.dist-info/WHEEL
p_system_simulate-0.0.4.dist-info/top_level.txt
p_system_simulate-0.0.4.dist-info/RECORD
