Metadata-Version: 2.1
Name: p-system-simulate
Version: 0.0.4
Summary: Library to simulate P Systems
Home-page: https://github.com/pablogl2002
Author: Pablo García López
Author-email: pablogl2002@gmail.com
License: UNKNOWN
Platform: UNKNOWN
